fb_pdnstools/__init__.py
fb_pdnstools/base_handler.py
fb_pdnstools/bulk_rm_app.py
fb_pdnstools/bulk_rm_cfg.py
fb_pdnstools/common.py
fb_pdnstools/errors.py
fb_pdnstools/record.py
fb_pdnstools/server.py
fb_pdnstools/xlate.py
fb_pdnstools/zone.py
fb_pdnstools-1.1.0.data/data/share/locale/de/LC_MESSAGES/fb_pdnstools.mo
fb_pdnstools-1.1.0.data/data/share/locale/en/LC_MESSAGES/fb_pdnstools.mo
fb_pdnstools-1.1.0.dist-info/entry_points.txt
fb_pdnstools-1.1.0.dist-info/licenses/LICENSE
fb_pdnstools-1.1.0.dist-info/WHEEL
fb_pdnstools-1.1.0.dist-info/METADATA
fb_pdnstools-1.1.0.dist-info/RECORD
