Metadata-Version: 2.4
Name: fb_pdnstools
Version: 1.1.0
Summary: @summary: The module for a base PowerDNS handler object.
Author-email: Frank Brehm <frank@brehm-online.com>
Requires-Python: >=3.8
Classifier: Development Status :: 4 - Beta
Classifier: Environment :: Console
Classifier: Framework :: IPython
Classifier: Intended Audience :: Developers
Classifier: License :: OSI Approved :: GNU Lesser General Public License v3 or later (LGPLv3+)
Classifier: Natural Language :: English
Classifier: Operating System :: POSIX
Classifier: Programming Language :: Python :: 3.9
Classifier: Programming Language :: Python :: 3.10
Classifier: Programming Language :: Python :: 3.11
Classifier: Programming Language :: Python :: 3.12
Classifier: Programming Language :: Python :: 3.13
Classifier: Topic :: Software Development :: Libraries :: Python Modules
License-File: LICENSE
Requires-Dist: babel
Requires-Dist: chardet
Requires-Dist: fb_logging
Requires-Dist: fb_tools
Requires-Dist: pytz
Requires-Dist: PyYAML
Requires-Dist: requests
Requires-Dist: semver
Requires-Dist: six
Requires-Dist: black ; extra == "development"
Requires-Dist: isort ; extra == "development"
Requires-Dist: hjson ; extra == "development"
Requires-Dist: flake8 ; extra == "lint"
Requires-Dist: pylint ; extra == "lint"
Requires-Dist: flake8-blind-except ; extra == "lint"
Requires-Dist: flake8-builtins ; extra == "lint"
Requires-Dist: flake8-bugbear ; extra == "lint"
Requires-Dist: flake8-class-newline ; extra == "lint"
Requires-Dist: flake8-comprehensions ; extra == "lint"
Requires-Dist: flake8-deprecated ; extra == "lint"
Requires-Dist: flake8-docstrings ; extra == "lint"
Requires-Dist: flake8-import-order ; extra == "lint"
Requires-Dist: pytest >= 7.0.0, < 9.0.0 ; extra == "testing"
Requires-Dist: requests_mock ; extra == "testing"
Project-URL: Source, https://github.com/fbrehm/fb-pdnstools
Provides-Extra: development
Provides-Extra: lint
Provides-Extra: testing
